puml2url/__init__.py
puml2url-0.0.0.dist-info/LICENSE
puml2url-0.0.0.dist-info/METADATA
puml2url-0.0.0.dist-info/WHEEL
puml2url-0.0.0.dist-info/top_level.txt
puml2url-0.0.0.dist-info/RECORD
